 {
  "name": "ROS 2 Humble Dev Container",
  "dockerComposeFile": "../docker-compose.yml",
  "service": "ros2-dev",
  "workspaceFolder": "/home/vscode/ros2_ws",
  "customizations": {
    "vscode": {
      "extensions": [
        "ms-vscode.cpptools-extension-pack",
        "xaver.clang-format",
        "llvm-vs-code-extensions.vscode-clangd",
        "twxs.cmake",
        "ms-vscode.cmake-tools",
        "ms-python.vscode-pylance",
        "ms-python.python",
        "ms-python.debugpy",
        "ms-python.vscode-python-envs",
        "Ranch-Hand-Robotics.rde-ros-2"
      ]
    }
  },

  "remoteUser": "vscode"
}